kunefe/__init__.py
kunefe/kunefe.py
kunefe/templates/generic_job.jinja
kunefe-0.5.1.dist-info/LICENSE
kunefe-0.5.1.dist-info/METADATA
kunefe-0.5.1.dist-info/NOTICE
kunefe-0.5.1.dist-info/WHEEL
kunefe-0.5.1.dist-info/top_level.txt
kunefe-0.5.1.dist-info/RECORD
