Metadata-Version: 2.1
Name: kunefe
Version: 0.5.1
Summary: A Python package to run containers on HPC systems
Author-email: "Faruk D." <f.diblen@esciencecenter.nl>
License: 
Project-URL: Repository, https://github.com/mess-nlesc/kunefe
Project-URL: Issues, https://github.com/mess-nlesc/kunefe/issues
Project-URL: Changelog, https://github.com/mess-nlesc/kunefe/CHANGELOG.md
Keywords: containers,hpc,slurm,docker,apptainer
Classifier: Development Status :: 2 - Pre-Alpha
Classifier: Intended Audience :: Developers
Classifier: Intended Audience :: Science/Research
Classifier: License :: OSI Approved :: Apache Software License
Classifier: Natural Language :: English
Classifier: Programming Language :: Python :: 3
Classifier: Programming Language :: Python :: 3.10
Classifier: Programming Language :: Python :: 3.11
Classifier: Programming Language :: Python :: 3.12
Requires-Python: >=3.10
License-File: LICENSE
License-File: NOTICE
Requires-Dist: paramiko ==3.4.0
Requires-Dist: jinja2 ==3.1.3
Provides-Extra: dev
Requires-Dist: build ; extra == 'dev'
Requires-Dist: bump-my-version ; extra == 'dev'
Requires-Dist: coverage[toml] ; extra == 'dev'
Requires-Dist: pytest ; extra == 'dev'
Requires-Dist: pytest-cov ; extra == 'dev'
Requires-Dist: ruff ; extra == 'dev'
Requires-Dist: sphinx ; extra == 'dev'
Requires-Dist: sphinx-rtd-theme ; extra == 'dev'
Requires-Dist: sphinx-autoapi ; extra == 'dev'
Requires-Dist: tox ; extra == 'dev'
Requires-Dist: myst-parser ; extra == 'dev'
Requires-Dist: mypy ; extra == 'dev'
Requires-Dist: docker ; extra == 'dev'
Requires-Dist: types-paramiko ; extra == 'dev'
Provides-Extra: publishing
Requires-Dist: build ; extra == 'publishing'
Requires-Dist: twine ; extra == 'publishing'
Requires-Dist: wheel ; extra == 'publishing'
